langgraph_checkpoint_snowflake/LICENSE
langgraph_checkpoint_snowflake/__init__.py
langgraph_checkpoint_snowflake/base.py
langgraph_checkpoint_snowflake/snowflakeSaver.py
langgraph_checkpoint_snowflake/snowflakeSerializer.py
langgraph_checkpoint_snowflake-0.1.0.dist-info/METADATA
langgraph_checkpoint_snowflake-0.1.0.dist-info/WHEEL
langgraph_checkpoint_snowflake-0.1.0.dist-info/RECORD
