Metadata-Version: 2.4
Name: langgraph_checkpoint_snowflake
Version: 0.1.0
Summary: Snowflake checkpoint saver implementation for LangGraph
Author-email: Kamal <skamalj@github.com>
Classifier: License :: OSI Approved :: MIT License
Classifier: Operating System :: OS Independent
Classifier: Programming Language :: Python :: 3
Requires-Python: >=3.9
Requires-Dist: langchain-core
Requires-Dist: langgraph
Requires-Dist: snowflake-connector-python
Provides-Extra: dev
Requires-Dist: black; extra == 'dev'
Requires-Dist: isort; extra == 'dev'
Requires-Dist: mypy; extra == 'dev'
Requires-Dist: pytest-cov; extra == 'dev'
Requires-Dist: pytest>=7.0; extra == 'dev'
